{
"title": "Word Salad 21",
"hintAnswerPairs": [
{"hint": "To withhold something from a person",
"answer": "dep ri ve",
"solved": false},
{"hint": "To bring something into existence",
"answer": "gen era te",
"solved": false},
{"hint": "Autumn beverage made from apples",
"answer": "ci der",
"solved": false},
{"hint": "Concentrated byproduct of processing sugar",
"answer": "mo las ses",
"solved": false},
{"hint": "To correct a mistake",
"answer": "re cti fy",
"solved": false},
{"hint": "To bring something back from the dead",
"answer": "res urr ect",
"solved": false}
],
"started": false,
"finished": false
}
