{
"title": "Word Salad 23",
"hintAnswerPairs": [
{"hint": "Seeming to happen without reason",
"answer": "ran dom",
"solved": false},
{"hint": "To make someone aware of their surroundings",
"answer": "o rie nt",
"solved": false},
{"hint": "Ordained member of the Catholic church",
"answer": "bis hop",
"solved": false},
{"hint": "Metal known for its electrical conductivity",
"answer": "Co pp er",
"solved": false},
{"hint": "Services and systems that serve a city",
"answer": "Inf ras tr uct ure",
"solved": false},
{"hint": "To make an idea or subject more understandable",
"answer": "cla ri fy",
"solved": false}
],
"started": false,
"finished": false
}
